vxsandbox/__init__.py
vxsandbox/protocol.py
vxsandbox/rlimiter.py
vxsandbox/utils.py
vxsandbox/worker.py
vxsandbox/resources/__init__.py
vxsandbox/resources/config.py
vxsandbox/resources/http.py
vxsandbox/resources/kv.py
vxsandbox/resources/logging.py
vxsandbox/resources/metrics.py
vxsandbox/resources/outbound.py
vxsandbox/resources/utils.py
vxsandbox/resources/tests/__init__.py
vxsandbox/resources/tests/test_config.py
vxsandbox/resources/tests/test_http.py
vxsandbox/resources/tests/test_kv.py
vxsandbox/resources/tests/test_logging.py
vxsandbox/resources/tests/test_metrics.py
vxsandbox/resources/tests/test_outbound.py
vxsandbox/resources/tests/test_utils.py
vxsandbox/resources/tests/utils.py
vxsandbox/tests/__init__.py
vxsandbox/tests/test_protocol.py
vxsandbox/tests/test_rlimiter.py
vxsandbox/tests/test_utils.py
vxsandbox/tests/test_worker.py
vxsandbox/tests/utils.py
vxsandbox-0.6.1.dist-info/DESCRIPTION.rst
vxsandbox-0.6.1.dist-info/METADATA
vxsandbox-0.6.1.dist-info/RECORD
vxsandbox-0.6.1.dist-info/WHEEL
vxsandbox-0.6.1.dist-info/metadata.json
vxsandbox-0.6.1.dist-info/top_level.txt
