Metadata-Version: 2.0
Name: vxsandbox
Version: 0.6.1
Summary: A sandbox application worker for Vumi.
Home-page: http://github.com/praekelt/vumi-sandbox
Author: Praekelt Foundation
Author-email: dev@praekeltfoundation.org
License: BSD
Platform: UNKNOWN
Classifier: Development Status :: 4 - Beta
Classifier: Intended Audience :: Developers
Classifier: License :: OSI Approved :: BSD License
Classifier: Operating System :: POSIX
Classifier: Programming Language :: Python
Classifier: Topic :: Software Development :: Libraries :: Python Modules
Classifier: Topic :: System :: Networking
Requires-Dist: Twisted (>=13.1.0)
Requires-Dist: vumi (>=0.5)
